zuper_zapp_interfaces.cpython-310-aarch64-linux-gnu.so
zuper_zapp_interfaces.pyi
zuper_zapp_interfaces_z7-7.3.2201252009.dist-info/METADATA
zuper_zapp_interfaces_z7-7.3.2201252009.dist-info/WHEEL
zuper_zapp_interfaces_z7-7.3.2201252009.dist-info/top_level.txt
zuper_zapp_interfaces_z7-7.3.2201252009.dist-info/zip-safe
zuper_zapp_interfaces_z7-7.3.2201252009.dist-info/RECORD
